itk_thinshelldemons.libs/libtbb-a0c974ac.so.12.3
itk/_ThinShellDemonsPython.so
itk/ThinShellDemonsPython.py
itk/itkThinShellDemonsMetricv4Python.py
itk/Configuration/ThinShellDemonsConfig.py
itk/Configuration/ThinShellDemons_snake_case.py
itk_thinshelldemons-0.1.1.dist-info/LICENSE
itk_thinshelldemons-0.1.1.dist-info/METADATA
itk_thinshelldemons-0.1.1.dist-info/top_level.txt
itk_thinshelldemons-0.1.1.dist-info/RECORD
itk_thinshelldemons-0.1.1.dist-info/WHEEL
